DFL168A/GPS.py
DFL168A/ISO15765.py
DFL168A/J1708.py
DFL168A/__init__.py
DFL168A/J1939/PGN57344.py
DFL168A/J1939/PGN61443.py
DFL168A/J1939/PGN61444.py
DFL168A/J1939/PGN61445.py
DFL168A/J1939/PGN64996.py
DFL168A/J1939/PGN65214.py
DFL168A/J1939/PGN65248.py
DFL168A/J1939/PGN65253.py
DFL168A/J1939/PGN65256.py
DFL168A/J1939/PGN65257.py
DFL168A/J1939/PGN65262.py
DFL168A/J1939/PGN65263.py
DFL168A/J1939/PGN65265.py
DFL168A/J1939/PGN65266.py
DFL168A/J1939/PGN65267.py
DFL168A/J1939/PGN65268.py
DFL168A/J1939/PGN65269.py
DFL168A/J1939/PGN65270.py
DFL168A/J1939/PGN65271.py
DFL168A/J1939/PGN65272.py
DFL168A/J1939/PGN65276.py
DFL168A/J1939/__init__.py
DFL168A-1.0.0.dist-info/LICENSE
DFL168A-1.0.0.dist-info/METADATA
DFL168A-1.0.0.dist-info/WHEEL
DFL168A-1.0.0.dist-info/top_level.txt
DFL168A-1.0.0.dist-info/RECORD
