Metadata-Version: 2.1
Name: DFL168A
Version: 1.0.0
Summary: The python module for OBD2/J1939/J1708 Interpreter IC: DFL168A from Dafulai Electronics Inc.
Home-page: https://github.com/Dafulai/DFL168A_Python
Author: Jack Xia
Author-email: techsupport@dafulaielectronics.com
License: UNKNOWN
Platform: UNKNOWN
Classifier: Programming Language :: Python :: 3
Classifier: License :: OSI Approved :: MIT License
Classifier: Operating System :: OS Independent
Requires-Python: >=3.6
